discontinuitypy-0.4.0.dist-info/METADATA
discontinuitypy-0.4.0.dist-info/WHEEL
discontinuitypy-0.4.0.dist-info/entry_points.txt
discontinuitypy/__init__.py
discontinuitypy/_modidx.py
discontinuitypy/config.py
discontinuitypy/core/__init__.py
discontinuitypy/core/pipeline.py
discontinuitypy/core/propeties.py
discontinuitypy/datasets.py
discontinuitypy/detection/__init__.py
discontinuitypy/detection/gradient.py
discontinuitypy/detection/variance.py
discontinuitypy/integration.py
discontinuitypy/mission/__init__.py
discontinuitypy/mission/solo.py
discontinuitypy/mission/stereo.py
discontinuitypy/mission/themis.py
discontinuitypy/mission/wind.py
discontinuitypy/naming.py
discontinuitypy/plot/__init__.py
discontinuitypy/plot/alfvenicity.py
discontinuitypy/propeties/__init__.py
discontinuitypy/propeties/duration.py
discontinuitypy/propeties/mva.py
discontinuitypy/propeties/normal.py
discontinuitypy/utils/__init__.py
discontinuitypy/utils/basic.py
discontinuitypy/utils/dataset.py
discontinuitypy/utils/naming.py
discontinuitypy/utils/ops.py
discontinuitypy/utils/plot.py
discontinuitypy-0.4.0.dist-info/RECORD
