Metadata-Version: 2.1
Name: discontinuitypy
Version: 0.4.0
Summary: A python package for identifying and analyzing discontinuities for time series data.
Author-Email: Beforerr <zzj956959688@gmail.com>
Project-URL: Homepage, https://beforerr.github.io/discontinuitypy
Project-URL: Repository, https://github.com/Beforerr/discontinuitypy
Requires-Python: >=3.10
Requires-Dist: space-analysis[io]
Requires-Dist: beforerr
Requires-Dist: xarray
Requires-Dist: xarray_einstats
Requires-Dist: polars
Requires-Dist: pyarrow
Requires-Dist: pydantic
Requires-Dist: scipy
Requires-Dist: fastcore
Requires-Dist: tqdm
Requires-Dist: loguru
Requires-Dist: ray
Provides-Extra: accel
Requires-Dist: xarray[accel]; extra == "accel"
Requires-Dist: numba; extra == "accel"
Provides-Extra: plot
Requires-Dist: matplotlib; extra == "plot"
Requires-Dist: pyspedas; extra == "plot"
Requires-Dist: hvplot>=0.10.0; extra == "plot"
Requires-Dist: holoviews; extra == "plot"
Provides-Extra: dev
Requires-Dist: ipykernel; extra == "dev"
Requires-Dist: nbdev; extra == "dev"
